earthkit/data/__init__.py
earthkit/data/_version.py
earthkit/data/decorators.py
earthkit/data/testing.py
earthkit/data/arguments/__init__.py
earthkit/data/arguments/args_kwargs.py
earthkit/data/arguments/argument.py
earthkit/data/arguments/earthkit_types.py
earthkit/data/arguments/input_manager.py
earthkit/data/arguments/transformers.py
earthkit/data/conf/global_grids.json
earthkit/data/conf/gridspec.yaml
earthkit/data/conf/gridspec_schema.json
earthkit/data/conf/css/tab.css
earthkit/data/conf/css/table.css
earthkit/data/conf/css/tree.css
earthkit/data/core/__init__.py
earthkit/data/core/caching.py
earthkit/data/core/config.py
earthkit/data/core/constants.py
earthkit/data/core/fieldlist.py
earthkit/data/core/geography.py
earthkit/data/core/gridspec.py
earthkit/data/core/index.py
earthkit/data/core/ipython.py
earthkit/data/core/metadata.py
earthkit/data/core/order.py
earthkit/data/core/plugins.py
earthkit/data/core/select.py
earthkit/data/core/statistics.py
earthkit/data/core/temporary.py
earthkit/data/core/thread.py
earthkit/data/encoders/__init__.py
earthkit/data/encoders/csv.py
earthkit/data/encoders/geotiff.py
earthkit/data/encoders/grib.py
earthkit/data/encoders/internal_pass_through.py
earthkit/data/encoders/netcdf.py
earthkit/data/encoders/zarr.py
earthkit/data/indexing/__init__.py
earthkit/data/indexing/cube.py
earthkit/data/indexing/fieldlist.py
earthkit/data/indexing/tensor.py
earthkit/data/indexing/database/__init__.py
earthkit/data/indexing/database/json.py
earthkit/data/indexing/database/sql.py
earthkit/data/indexing/database/stdout.py
earthkit/data/mergers/__init__.py
earthkit/data/mergers/pandas.py
earthkit/data/mergers/xarray.py
earthkit/data/mirrors/__init__.py
earthkit/data/mirrors/directory_mirror.py
earthkit/data/readers/__init__.py
earthkit/data/readers/archive.py
earthkit/data/readers/covjson.py
earthkit/data/readers/csv.py
earthkit/data/readers/directory.py
earthkit/data/readers/geojson.py
earthkit/data/readers/geotiff.py
earthkit_data-0.18.4.dist-info/licenses/LICENCE
earthkit_data-0.18.4.dist-info/METADATA
earthkit_data-0.18.4.dist-info/WHEEL
earthkit_data-0.18.4.dist-info/entry_points.txt
earthkit_data-0.18.4.dist-info/top_level.txt
earthkit_data-0.18.4.dist-info/RECORD
