Metadata-Version: 2.4
Name: earthkit-data
Version: 0.18.4
Summary: A format-agnostic Python interface for geospatial data
Author-email: "European Centre for Medium-Range Weather Forecasts (ECMWF)" <software.support@ecmwf.int>
License: Apache License Version 2.0
Project-URL: Documentation, https://earthkit-data.readthedocs.io/
Project-URL: Homepage, https://github.com/ecmwf/earthkit-data/
Project-URL: Issues, https://github.com/ecmwf/earthkit-data.issues
Project-URL: Repository, https://github.com/ecmwf/earthkit-data/
Classifier: Development Status :: 2 - Pre-Alpha
Classifier: Intended Audience :: Developers
Classifier: License :: OSI Approved :: Apache Software License
Classifier: Operating System :: OS Independent
Classifier: Programming Language :: Python :: 3 :: Only
Classifier: Programming Language :: Python :: 3.9
Classifier: Programming Language :: Python :: 3.10
Classifier: Programming Language :: Python :: 3.11
Classifier: Programming Language :: Python :: 3.12
Classifier: Programming Language :: Python :: 3.13
Classifier: Programming Language :: Python :: Implementation :: CPython
Classifier: Programming Language :: Python :: Implementation :: PyPy
Requires-Python: >=3.9
License-File: LICENCE
Requires-Dist: cfgrib>=0.9.10.1
Requires-Dist: dask
Requires-Dist: deprecation
Requires-Dist: earthkit-meteo>=0.0.1
Requires-Dist: earthkit-utils>=0.1.1
Requires-Dist: eccodes>=1.7
Requires-Dist: entrypoints
Requires-Dist: filelock
Requires-Dist: jinja2
Requires-Dist: jsonschema
Requires-Dist: lru-dict
Requires-Dist: markdown
Requires-Dist: multiurl>=0.3.3
Requires-Dist: netcdf4!=1.7.4
Requires-Dist: pandas
Requires-Dist: pdbufr>=0.11
Requires-Dist: pyyaml
Requires-Dist: tqdm>=4.63
Requires-Dist: xarray>=0.19
Provides-Extra: all
Requires-Dist: earthkit-data[cds,covjsonkit,ecmwf-opendata,fdb,geo,geopandas,gribjump,mars,odb,polytope,projection,s3,wekeo]; extra == "all"
Provides-Extra: cds
Requires-Dist: cdsapi>=0.7.2; extra == "cds"
Provides-Extra: ci
Requires-Dist: numpy; extra == "ci"
Provides-Extra: covjsonkit
Requires-Dist: covjsonkit>=0.2.2; extra == "covjsonkit"
Provides-Extra: dev
Requires-Dist: earthkit-data[all,docs,test]; extra == "dev"
Provides-Extra: docs
Requires-Dist: nbsphinx; extra == "docs"
Requires-Dist: pygments>=2.6.1; extra == "docs"
Requires-Dist: sphinx>=7.3.7; extra == "docs"
Requires-Dist: sphinx-autoapi; extra == "docs"
Requires-Dist: sphinx-copybutton; extra == "docs"
Requires-Dist: sphinx-issues; extra == "docs"
Requires-Dist: sphinx-rtd-theme; extra == "docs"
Requires-Dist: sphinx-tabs; extra == "docs"
Provides-Extra: ecmwf-opendata
Requires-Dist: ecmwf-opendata>=0.3.3; extra == "ecmwf-opendata"
Provides-Extra: fdb
Requires-Dist: pyfdb>=0.1; extra == "fdb"
Provides-Extra: geo
Requires-Dist: earthkit-geo>=0.2; extra == "geo"
Provides-Extra: geopandas
Requires-Dist: geopandas; extra == "geopandas"
Provides-Extra: geotiff
Requires-Dist: pyproj; extra == "geotiff"
Requires-Dist: rasterio; extra == "geotiff"
Requires-Dist: rioxarray; extra == "geotiff"
Provides-Extra: gribjump
Requires-Dist: pyfdb>=0.1; extra == "gribjump"
Requires-Dist: pygribjump; extra == "gribjump"
Provides-Extra: mars
Requires-Dist: ecmwf-api-client>=1.6.1; extra == "mars"
Provides-Extra: odb
Requires-Dist: pyodc; extra == "odb"
Provides-Extra: polytope
Requires-Dist: polytope-client>=0.7.6; extra == "polytope"
Provides-Extra: projection
Requires-Dist: cartopy; extra == "projection"
Provides-Extra: s3
Requires-Dist: aws-requests-auth; extra == "s3"
Requires-Dist: botocore; extra == "s3"
Provides-Extra: test
Requires-Dist: earthkit-data-demo-source; extra == "test"
Requires-Dist: nbconvert; extra == "test"
Requires-Dist: nbformat; extra == "test"
Requires-Dist: pyfakefs; extra == "test"
Requires-Dist: pytest; extra == "test"
Requires-Dist: pytest-cov; extra == "test"
Requires-Dist: pytest-forked; extra == "test"
Requires-Dist: pytest-reraise; extra == "test"
Requires-Dist: pytest-timeout; extra == "test"
Provides-Extra: wekeo
Requires-Dist: hda>=2.22; extra == "wekeo"
Provides-Extra: zarr
Requires-Dist: zarr>=3; extra == "zarr"
Dynamic: license-file
